django_sofortueberweisung/__init__.py
django_sofortueberweisung/admin.py
django_sofortueberweisung/cacert.pem
django_sofortueberweisung/models.py
django_sofortueberweisung/settings.py
django_sofortueberweisung/urls.py
django_sofortueberweisung/views.py
django_sofortueberweisung/wrappers.py
django_sofortueberweisung/migrations/0001_initial.py
django_sofortueberweisung/migrations/0002_auto_20190211_1320.py
django_sofortueberweisung/migrations/__init__.py
django_sofortueberweisung/templates/django_sofortueberweisung/transaction_init.xml
django_sofortueberweisung/templates/django_sofortueberweisung/transaction_refund.xml
django_sofortueberweisung/templates/django_sofortueberweisung/transaction_update.xml
django_sofortueberweisung-1.0.0.dist-info/LICENSE
django_sofortueberweisung-1.0.0.dist-info/METADATA
django_sofortueberweisung-1.0.0.dist-info/WHEEL
django_sofortueberweisung-1.0.0.dist-info/top_level.txt
django_sofortueberweisung-1.0.0.dist-info/RECORD
