Metadata-Version: 2.1
Name: django-sofortueberweisung
Version: 1.0.0
Summary: Django integration of Sofort.com
Home-page: https://github.com/ParticulateSolutions/django-sofortueberweisung
Author: Particulate Solutions GmbH
Author-email: tech@particulate.me
Classifier: Environment :: Web Environment
Classifier: Intended Audience :: Developers
Classifier: License :: OSI Approved :: MIT License
Classifier: Operating System :: OS Independent
Classifier: Programming Language :: Python
Classifier: Programming Language :: Python :: 2.7
Classifier: Programming Language :: Python :: 3.4
Classifier: Programming Language :: Python :: 3.5
Classifier: Framework :: Django
Classifier: Topic :: Software Development :: Libraries :: Application Frameworks
Classifier: Topic :: Software Development :: Libraries :: Python Modules
License-File: LICENSE
Requires-Dist: Django >=4.0
Requires-Dist: xmltodict >=0.9.2
